{
  "paris": [
    {
      "type": "ULTRA SAFE",
      "style": "Simple",
      "match": "France vs Senegal",
      "competition": "FIFA World Cup",
      "heure": "16/06 20:00",
      "selection": "Victoire France",
      "cote": 1.5,
      "bookmaker": "1xBet",
      "mise_tnd": 4.0,
      "ev_pct": 10.0,
      "raison": "Probabilité élevée de victoire de la France"
    },
    {
      "type": "VALEUR",
      "style": "Simple",
      "match": "Boston Red Sox vs Toronto Blue Jays",
      "competition": "MLB",
      "heure": "16/06 23:45",
      "selection": "Victoire Toronto Blue Jays",
      "cote": 1.88,
      "bookmaker": "1xBet",
      "mise_tnd": 2.5,
      "ev_pct": 8.0,
      "raison": "Cote sous-évaluée pour la victoire des Blue Jays"
    },
    {
      "type": "OPPORTUNISTE",
      "style": "Combiné",
      "match": "France vs Senegal",
      "competition": "FIFA World Cup",
      "heure": "16/06 20:00",
      "selection": "Victoire France et Plus de 2.5",
      "cote": 2.5,
      "bookmaker": "Pinnacle",
      "mise_tnd": 1.5,
      "ev_pct": 12.0,
      "raison": "Combiné logique à combiner avec le match Iraq vs Norway"
    },
    {
      "type": "OPPORTUNISTE",
      "style": "Combiné",
      "match": "Iraq vs Norway",
      "competition": "FIFA World Cup",
      "heure": "16/06 23:00",
      "selection": "Plus de 2.5 et Victoire Norway",
      "cote": 2.5,
      "bookmaker": "Pinnacle",
      "mise_tnd": 1.5,
      "ev_pct": 12.0,
      "raison": "Combiné logique à combiner avec le match France vs Senegal"
    }
  ],
  "note_du_jour": "Journée avec quelques opportunités intéressantes",
  "confiance": "Moyen"
}